jalali_pandas/__init__.py
jalali_pandas/_typing.py
jalali_pandas/_version.py
jalali_pandas/df_handler.py
jalali_pandas/py.typed
jalali_pandas/serie_handler.py
jalali_pandas/accessors/__init__.py
jalali_pandas/accessors/dataframe.py
jalali_pandas/accessors/series.py
jalali_pandas/api/__init__.py
jalali_pandas/api/conversion.py
jalali_pandas/api/date_range.py
jalali_pandas/api/grouper.py
jalali_pandas/compat/__init__.py
jalali_pandas/compat/legacy.py
jalali_pandas/core/__init__.py
jalali_pandas/core/arrays.py
jalali_pandas/core/calendar.py
jalali_pandas/core/conversion.py
jalali_pandas/core/dtypes.py
jalali_pandas/core/indexes.py
jalali_pandas/core/timestamp.py
jalali_pandas/offsets/__init__.py
jalali_pandas/offsets/aliases.py
jalali_pandas/offsets/base.py
jalali_pandas/offsets/month.py
jalali_pandas/offsets/quarter.py
jalali_pandas/offsets/week.py
jalali_pandas/offsets/year.py
jalali_pandas-1.0.0.dist-info/METADATA
jalali_pandas-1.0.0.dist-info/WHEEL
jalali_pandas-1.0.0.dist-info/licenses/LICENSE
jalali_pandas-1.0.0.dist-info/RECORD
