Metadata-Version: 2.4
Name: jalali-pandas
Version: 1.0.0
Summary: Full Jalali calendar support for pandas time series
Project-URL: Documentation, https://ghodsizadeh.github.io/jalali-pandas/
Project-URL: Homepage, https://ghodsizadeh.github.io/jalali-pandas/
Project-URL: Repository, https://github.com/ghodsizadeh/jalali-pandas
Project-URL: Changelog, https://github.com/ghodsizadeh/jalali-pandas/blob/main/CHANGELOG.md
Project-URL: Bug Tracker, https://github.com/ghodsizadeh/jalali-pandas/issues
Author-email: Mehdi Ghodsizadeh <mehdi.ghodsizadeh@gmail.com>
License:                     GNU AFFERO GENERAL PUBLIC LICENSE
License-File: LICENSE
Keywords: calendar,datetime,jalali,pandas,persian,shamsi,timeseries
Classifier: Development Status :: 5 - Production/Stable
Classifier: Intended Audience :: Developers
Classifier: Intended Audience :: Science/Research
Classifier: License :: OSI Approved :: GNU General Public License v3 (GPLv3)
Classifier: Operating System :: OS Independent
Classifier: Programming Language :: Python :: 3
Classifier: Programming Language :: Python :: 3 :: Only
Classifier: Programming Language :: Python :: 3.9
Classifier: Programming Language :: Python :: 3.10
Classifier: Programming Language :: Python :: 3.11
Classifier: Programming Language :: Python :: 3.12
Classifier: Programming Language :: Python :: 3.13
Classifier: Topic :: Scientific/Engineering
Classifier: Topic :: Software Development :: Libraries :: Python Modules
Classifier: Typing :: Typed
Requires-Python: >=3.9
Requires-Dist: jdatetime>=4.0.0
Requires-Dist: numpy>=1.23.0
Requires-Dist: pandas>=2.0.0
Requires-Dist: typing-extensions>=4.0.0
Provides-Extra: all
Requires-Dist: hypothesis>=6.0.0; extra == 'all'
Requires-Dist: mkdocs-gen-files>=0.5.0; extra == 'all'
Requires-Dist: mkdocs-literate-nav>=0.6.0; extra == 'all'
Requires-Dist: mkdocs-material>=9.0.0; extra == 'all'
Requires-Dist: mkdocs>=1.5.0; extra == 'all'
Requires-Dist: mkdocstrings[python]>=0.24.0; extra == 'all'
Requires-Dist: mypy>=1.0.0; extra == 'all'
Requires-Dist: pandas-stubs; extra == 'all'
Requires-Dist: pre-commit>=3.0.0; extra == 'all'
Requires-Dist: pyright>=1.1.0; extra == 'all'
Requires-Dist: pytest-cov>=4.0.0; extra == 'all'
Requires-Dist: pytest-xdist>=3.0.0; extra == 'all'
Requires-Dist: pytest>=7.0.0; extra == 'all'
Requires-Dist: ruff>=0.1.0; extra == 'all'
Provides-Extra: dev
Requires-Dist: hypothesis>=6.0.0; extra == 'dev'
Requires-Dist: mypy>=1.0.0; extra == 'dev'
Requires-Dist: pandas-stubs; extra == 'dev'
Requires-Dist: pre-commit>=3.0.0; extra == 'dev'
Requires-Dist: pyright>=1.1.0; extra == 'dev'
Requires-Dist: pytest-cov>=4.0.0; extra == 'dev'
Requires-Dist: pytest-xdist>=3.0.0; extra == 'dev'
Requires-Dist: pytest>=7.0.0; extra == 'dev'
Requires-Dist: ruff>=0.1.0; extra == 'dev'
Provides-Extra: docs
Requires-Dist: mkdocs-gen-files>=0.5.0; extra == 'docs'
Requires-Dist: mkdocs-literate-nav>=0.6.0; extra == 'docs'
Requires-Dist: mkdocs-material>=9.0.0; extra == 'docs'
Requires-Dist: mkdocs>=1.5.0; extra == 'docs'
Requires-Dist: mkdocstrings[python]>=0.24.0; extra == 'docs'
